iampoliciesgonewild/__init__.py
iampoliciesgonewild/master_permissions.json
iampoliciesgonewild/data/master_permissions.json
iampoliciesgonewild-1.0.5.dist-info/DESCRIPTION.rst
iampoliciesgonewild-1.0.5.dist-info/METADATA
iampoliciesgonewild-1.0.5.dist-info/metadata.json
iampoliciesgonewild-1.0.5.dist-info/RECORD
iampoliciesgonewild-1.0.5.dist-info/top_level.txt
iampoliciesgonewild-1.0.5.dist-info/WHEEL
