Metadata-Version: 2.0
Name: iampoliciesgonewild
Version: 1.0.5
Summary: AWS IAM Policy Expander Minimizer
Home-page: https://github.com/monkeysecurity/iampoliciesgonewild
Author: Patrick Kelley
Author-email: pkelley@netflix.com
License: UNKNOWN
Keywords: iam,policy,wildcard
Platform: UNKNOWN
